economic_agents/__init__.py
economic_agents/charness_rabin.py
economic_agents/horton.py
economic_agents/kahneman.py
economic_agents/open_ai.py
economic_agents/zeckhauser.py
economic_agents-0.1.dist-info/METADATA
economic_agents-0.1.dist-info/WHEEL
economic_agents-0.1.dist-info/top_level.txt
economic_agents-0.1.dist-info/RECORD
